axial_positional_embedding/__init__.py
axial_positional_embedding/axial_positional_embedding.py
axial_positional_embedding/continuous_axial_positional_embedding.py
axial_positional_embedding-0.3.10.dist-info/METADATA
axial_positional_embedding-0.3.10.dist-info/WHEEL
axial_positional_embedding-0.3.10.dist-info/licenses/LICENSE
axial_positional_embedding-0.3.10.dist-info/RECORD
