Metadata-Version: 2.4
Name: axial_positional_embedding
Version: 0.3.10
Summary: Axial Positional Embedding
Project-URL: Homepage, https://pypi.org/project/axial_positional_embedding/
Project-URL: Repository, https://github.com/lucidrains/axial_positional_embedding
Author-email: Phil Wang <lucidrains@gmail.com>
License: MIT License
License-File: LICENSE
Keywords: artificial intelligence,deep learning,positional embedding
Classifier: Development Status :: 4 - Beta
Classifier: Intended Audience :: Developers
Classifier: License :: OSI Approved :: MIT License
Classifier: Programming Language :: Python :: 3.8
Classifier: Topic :: Scientific/Engineering :: Artificial Intelligence
Requires-Python: >=3.8
Requires-Dist: einops>=0.8.0
Requires-Dist: torch>=2.0
Provides-Extra: examples
